var correos = [{
"type": "FeatureCollection",
"crs": { "type": "name", "properties": { "name": "urn:ogc:def:crs:OGC:1.3:CRS84" } },
                                                                                
"features": [
{ "type": "Feature", "properties": { "id": 1, "Nombre": "Correos CR", "Locacion": null }, "geometry": { "type": "Point", "coordinates": [ -84.0622013, 9.8964982 ] } },
{ "type": "Feature", "properties": { "id": 2, "Nombre": "Aerocasillas", "Locacion": null }, "geometry": { "type": "Point", "coordinates": [ -84.0609591, 9.9021586 ] } },
{ "type": "Feature", "properties": { "id": 3, "Nombre": "Correos de Costa Rica", "Locacion": "De la estacion de Bomberos, 100 metros sur" }, "geometry": { "type": "Point", "coordinates": [ -84.0622255, 9.8959609 ] } }
]
}]